package_Ygor/__init__.py
package_Ygor/module1_name/Combination.py
package_Ygor/module1_name/Transformation.py
package_Ygor/module1_name/__init__.py
package_Ygor/module2_name/Io.py
package_Ygor/module2_name/Plot.py
package_Ygor/module2_name/__init__.py
package_Ygor-0.0.3.dist-info/METADATA
package_Ygor-0.0.3.dist-info/WHEEL
package_Ygor-0.0.3.dist-info/top_level.txt
package_Ygor-0.0.3.dist-info/RECORD
