Metadata-Version: 2.1
Name: package-Ygor
Version: 0.0.3
Summary: Test version - Image processing. This project belongs to Karina Tiemi Kato, Tech Lead, Machine Learning Engineer, Data Scientist Specialist at Take. This package is a demo for simulation of upload on the Test Pypi website, and it's from class of the Bootcamp developer full stack Python. E-mail:karinatkato@gmail.com.
Author: ygor silva lino teixeira
Author-email: ygor-1996@hotmail.com
Requires-Python: >=3.8
Requires-Dist: bleach (==3.1.5)
Requires-Dist: certifi (==2020.6.20)
Requires-Dist: chardet (==3.0.4)
Requires-Dist: colorama (==0.4.3)
Requires-Dist: docutils (==0.16)
Requires-Dist: idna (==2.10)
Requires-Dist: keyring (==21.3.1)
Requires-Dist: packaging (==20.4)
Requires-Dist: pkginfo (==1.5.0.1)
Requires-Dist: Pygments (==2.6.1)
Requires-Dist: pyparsing (==2.4.7)
Requires-Dist: pywin32-ctypes (==0.2.0)
Requires-Dist: readme-renderer (==26.0)
Requires-Dist: requests (==2.24.0)
Requires-Dist: requests-toolbelt (==0.9.1)
Requires-Dist: rfc3986 (==1.4.0)
Requires-Dist: six (==1.15.0)
Requires-Dist: tqdm (==4.48.2)
Requires-Dist: twine (==3.2.0)
Requires-Dist: urllib3 (==1.25.10)
Requires-Dist: webencodings (==0.5.1)
